setup.py
jde/__init__.py
jde.egg-info/PKG-INFO
jde.egg-info/SOURCES.txt
jde.egg-info/dependency_links.txt
jde.egg-info/not-zip-safe
jde.egg-info/top_level.txt