Metadata-Version: 1.0
Name: jde
Version: 0.1
Summary: Jupyter Integrated Development Environment
Home-page: http://github.com/ebanner/jde
Author: Edward Banner
Author-email: edward.banner@gmail.com
License: MIT
Platform: UNKNOWN
